kmds/__init__.py
kmds/cloud_readers/__init__.py
kmds/cloud_readers/boxreader.py
kmds/cloud_readers/cloud_data_reader.py
kmds/cloud_readers/minioreader.py
kmds/cloud_writers/cloud_data_writer.py
kmds/cloud_writers/miniowriter.py
kmds/config/kmds_app.yml
kmds/examples/data_types_ITSM.csv
kmds/examples/example_analytics_data_rep1_meta_data.csv
kmds/examples/example_analytics_kb_app_workflow.xml
kmds/examples/example_analytics_post_data_rep1_data.csv
kmds/examples/example_analytics_post_data_rep_data.csv
kmds/examples/example_ml_kb_exp_workflow.xml
kmds/examples/incident_event_log_02.csv
kmds/examples/online_retail_Q1_2010.parquet
kmds/examples/q2_2016_ticket_resolution_data.csv
kmds/examples/retail_q1_post_EDA.parquet
kmds/examples/retail_q1_post_data_rep_prep.parquet
kmds/examples/retail_q1_post_mc.parquet
kmds/examples/retail_q1_sales_2010_summary.parquet
kmds/examples/retail_transformed_q1_product_data.parquet
kmds/examples/retail_transformed_q1_sales_data.parquet
kmds/examples/test_kb_app_workflow
kmds/examples/test_kb_app_workflow.xml
kmds/examples/test_kb_exp_workflow
kmds/examples/test_kb_exp_workflow.xml
kmds/examples/ticket_resolution_Q2_2016.csv
kmds/examples/ticket_resolution_dtypes.csv
kmds/ontology/__init__.py
kmds/ontology/intent_types.py
kmds/ontology/kmds_ontology.py
kmds/ontology/kmds_ontology.xml
kmds/pipelines/__init__.py
kmds/pipelines/retail_processing.py
kmds/tagging/__init__.py
kmds/tagging/tag_types.py
kmds/utils/__init__.py
kmds/utils/config_reader.py
kmds/utils/load_utils.py
kmds/utils/path_utils.py
kmds-0.2.16.dist-info/METADATA
kmds-0.2.16.dist-info/WHEEL
kmds-0.2.16.dist-info/RECORD
