Metadata-Version: 2.1
Name: kmds
Version: 0.2.16
Summary: This is a package that helps data scientists and data analysts to capture notes while they work through data science tasks. The captured tasks can then be searched and analyzed.
License: Apache 2.0
Author: Rajiv Sambasivan
Author-email: rajiv.sambasivan@r2-ds.com
Requires-Python: >=3.10,<4.0
Classifier: License :: Other/Proprietary License
Classifier: Programming Language :: Python :: 3
Classifier: Programming Language :: Python :: 3.10
Classifier: Programming Language :: Python :: 3.11
Classifier: Programming Language :: Python :: 3.12
Requires-Dist: Flask (>=3.0.2,<4.0.0)
Requires-Dist: PyYAML (>=6.0.1,<7.0.0)
Requires-Dist: owlready2 (>=0.45,<0.46)
Requires-Dist: pytest (>=8.0.0,<9.0.0)
Requires-Dist: rdflib (>=7.0.0,<8.0.0)
